COPYING
MANIFEST.in
README.rst
setup.py
pylesswrap/__init__.py
pylesswrap/django_finders.py
pylesswrap/less.py
pylesswrap/pipeline_compiler.py
pylesswrap.egg-info/PKG-INFO
pylesswrap.egg-info/SOURCES.txt
pylesswrap.egg-info/dependency_links.txt
pylesswrap.egg-info/top_level.txt